CHANGES.rst
CONTRIBUTORS.rst
MANIFEST.in
README.rst
setup.cfg
setup.py
docs/LICENSE.GPL
docs/LICENSE.rst
docs/index.rst
src/collective/__init__.py
src/collective.ptg.unitegallery.egg-info/PKG-INFO
src/collective.ptg.unitegallery.egg-info/SOURCES.txt
src/collective.ptg.unitegallery.egg-info/dependency_links.txt
src/collective.ptg.unitegallery.egg-info/entry_points.txt
src/collective.ptg.unitegallery.egg-info/namespace_packages.txt
src/collective.ptg.unitegallery.egg-info/not-zip-safe
src/collective.ptg.unitegallery.egg-info/requires.txt
src/collective.ptg.unitegallery.egg-info/top_level.txt
src/collective/ptg/__init__.py
src/collective/ptg/unitegallery/__init__.py
src/collective/ptg/unitegallery/carousel.py
src/collective/ptg/unitegallery/compact.py
src/collective/ptg/unitegallery/configure.zcml
src/collective/ptg/unitegallery/default.py
src/collective/ptg/unitegallery/grid.py
src/collective/ptg/unitegallery/interfaces.py
src/collective/ptg/unitegallery/setuphandlers.py
src/collective/ptg/unitegallery/slider.py
src/collective/ptg/unitegallery/tiles.py
src/collective/ptg/unitegallery/tilesgrid.py
src/collective/ptg/unitegallery/unitegallery.pt
src/collective/ptg/unitegallery/video.py
src/collective/ptg/unitegallery/locales/collective.ptg.unitegallery.pot
src/collective/ptg/unitegallery/locales/update.sh
src/collective/ptg/unitegallery/profiles/default/browserlayer.xml
src/collective/ptg/unitegallery/profiles/default/metadata.xml
src/collective/ptg/unitegallery/profiles/uninstall/browserlayer.xml
src/collective/ptg/unitegallery/resources/.gitkeep
src/collective/ptg/unitegallery/resources/css/unite-gallery.css
src/collective/ptg/unitegallery/resources/images/button-close.png
src/collective/ptg/unitegallery/resources/images/cover-grid.png
src/collective/ptg/unitegallery/resources/images/icon-link32.png
src/collective/ptg/unitegallery/resources/images/icon-play32.png
src/collective/ptg/unitegallery/resources/images/icon-zoom32.png
src/collective/ptg/unitegallery/resources/images/lightbox-arrow-left.png
src/collective/ptg/unitegallery/resources/images/lightbox-arrow-right.png
src/collective/ptg/unitegallery/resources/images/lightbox-icon-close-compact.png
src/collective/ptg/unitegallery/resources/images/lightbox-icon-close-compact2.png
src/collective/ptg/unitegallery/resources/images/lightbox-icon-close.png
src/collective/ptg/unitegallery/resources/images/loader-black1.gif
